onegov.swissvotes-1.2.5-py3.6-nspkg.pth
onegov/swissvotes/.gitignore
onegov/swissvotes/__init__.py
onegov/swissvotes/app.py
onegov/swissvotes/cli.py
onegov/swissvotes/path.py
onegov/swissvotes/upgrade.py
onegov/swissvotes/assets/css/jquery.datetimepicker.css
onegov/swissvotes/assets/css/react-dropdown-tree-select.css
onegov/swissvotes/assets/css/tablesaw.css
onegov/swissvotes/assets/js/common.js
onegov/swissvotes/assets/js/confirm.jsx
onegov/swissvotes/assets/js/d3.chart.bar.js
onegov/swissvotes/assets/js/d3.js
onegov/swissvotes/assets/js/datetimepicker.js
onegov/swissvotes/assets/js/dropzone.js
onegov/swissvotes/assets/js/foundation.js
onegov/swissvotes/assets/js/intercooler.js
onegov/swissvotes/assets/js/jquery.datetimepicker.js
onegov/swissvotes/assets/js/jquery.js
onegov/swissvotes/assets/js/jquery.tablesorter.js
onegov/swissvotes/assets/js/modernizr.js
onegov/swissvotes/assets/js/policy-selector.jsx
onegov/swissvotes/assets/js/react-dom.js
onegov/swissvotes/assets/js/react-dropdown-tree-select.js
onegov/swissvotes/assets/js/react.js
onegov/swissvotes/assets/js/sortable.js
onegov/swissvotes/assets/js/sortable_custom.js
onegov/swissvotes/assets/js/tablesaw-create.js
onegov/swissvotes/assets/js/tablesaw-init.js
onegov/swissvotes/assets/js/tablesaw.jquery.js
onegov/swissvotes/assets/js/underscore.js
onegov/swissvotes/assets/js/__tests__/__snapshots__/d3.chart.bar.js.snap
onegov/swissvotes/collections/__init__.py
onegov/swissvotes/collections/pages.py
onegov/swissvotes/collections/votes.py
onegov/swissvotes/fields/__init__.py
onegov/swissvotes/fields/dataset.py
onegov/swissvotes/fields/policy_area.py
onegov/swissvotes/forms/__init__.py
onegov/swissvotes/forms/attachments.py
onegov/swissvotes/forms/page.py
onegov/swissvotes/forms/search.py
onegov/swissvotes/forms/update_dataset.py
onegov/swissvotes/layouts/__init__.py
onegov/swissvotes/layouts/default.py
onegov/swissvotes/layouts/mail.py
onegov/swissvotes/layouts/page.py
onegov/swissvotes/layouts/vote.py
onegov.swissvotes-1.2.5.dist-info/METADATA
onegov.swissvotes-1.2.5.dist-info/WHEEL
onegov.swissvotes-1.2.5.dist-info/entry_points.txt
onegov.swissvotes-1.2.5.dist-info/namespace_packages.txt
onegov.swissvotes-1.2.5.dist-info/top_level.txt
onegov.swissvotes-1.2.5.dist-info/RECORD
